granadilla/__init__.py
granadilla/admin.py
granadilla/cli.py
granadilla/cli_settings.py
granadilla/conf.py
granadilla/forms.py
granadilla/models.py
granadilla/urls.py
granadilla/vcard.py
granadilla/version.py
granadilla/views.py
granadilla/locale/fr/LC_MESSAGES/django.mo
granadilla/locale/fr/LC_MESSAGES/django.po
granadilla/static/granadilla/css/base.css
granadilla/static/granadilla/img/.addicons
granadilla/static/granadilla/img/contact.png
granadilla/static/granadilla/img/contact.svg
granadilla/static/granadilla/img/device.png
granadilla/static/granadilla/img/group.png
granadilla/static/granadilla/img/group.svg
granadilla/static/granadilla/img/image.png
granadilla/static/granadilla/img/image.svg
granadilla/static/granadilla/img/unknown.png
granadilla/static/granadilla/img/user.png
granadilla/static/granadilla/img/user.svg
granadilla/templates/granadilla/base.html
granadilla/templates/granadilla/change_password.html
granadilla/templates/granadilla/device.html
granadilla/templates/granadilla/device_attr.html
granadilla/templates/granadilla/device_base.html
granadilla/templates/granadilla/device_delete.html
granadilla/templates/granadilla/device_list.html
granadilla/templates/granadilla/device_password.html
granadilla/templates/granadilla/group.html
granadilla/templates/granadilla/group_list.html
granadilla/templates/granadilla/photo_delete.html
granadilla/templates/granadilla/user.html
granadilla/templatetags/__init__.py
granadilla/templatetags/granadilla_tags.py
granadilla_webapp/__init__.py
granadilla_webapp/settings.py
granadilla_webapp/urls.py
granadilla_webapp/wsgi.py
granadilla_webapp/web/__init__.py
granadilla_webapp/web/models.py
granadilla_webapp/web/templates/404.html
granadilla_webapp/web/templates/base.html
granadilla_webapp/web/templates/registration/logged_out.html
granadilla_webapp/web/templates/registration/login.html
tests/__init__.py
tests/test_granadilla.py
granadilla-0.7.3.dist-info/COPYING
granadilla-0.7.3.dist-info/METADATA
granadilla-0.7.3.dist-info/WHEEL
granadilla-0.7.3.dist-info/top_level.txt
granadilla-0.7.3.dist-info/RECORD
