Metadata-Version: 2.1
Name: granadilla
Version: 0.7.3
Summary: An opinionated LDAP frontend.
Home-page: https://github.com/Polyconseil/granadilla
Author: Polyconseil Sysadmin Team
Author-email: sysadmin+granadilla@polyconseil.fr
License: GPL
Keywords: granadilla,ldap,directory,admin
Platform: UNKNOWN
Classifier: Development Status :: 4 - Beta
Classifier: Environment :: Web Environment
Classifier: Environment :: Console
Classifier: Framework :: Django :: 2.1
Classifier: Intended Audience :: System Administrators
Classifier: License :: OSI Approved :: GNU General Public License v3 (GPLv3)
Classifier: Programming Language :: Python :: 3.5
Classifier: Programming Language :: Python :: 3.6
Classifier: Topic :: System :: Systems Administration :: Authentication/Directory :: LDAP
Requires-Dist: django-ldapdb
Requires-Dist: django-auth-ldap
Requires-Dist: django-appconf
Requires-Dist: getconf (>=1.2.0)
Requires-Dist: django-zxcvbn-password (>=2.0.0)
Requires-Dist: django-password-strength (>=1.2.1)
Requires-Dist: zxcvbn
Requires-Dist: colorama
